{
  "schema_version": "v2", "id": "marketing-and-branding/brand-recall-color-match",
  "title": {"en": "Brand Recall by Colour — Tiffany Blue, Coca-Cola Red", "ko": "색상 브랜드 기억 — 티파니 블루, 코카콜라 레드"},
  "subtitle": {"en": "Colour drives 80% of brand recognition; brands trademark specific Pantones — PMS 1837 (Tiffany), PMS 219 (T-Mobile), Pullman Brown (UPS)", "ko": "색상이 브랜드 인식 80% 견인; 특정 Pantone 상표 등록 — PMS 1837(티파니), PMS 219(T-모바일), Pullman Brown(UPS)"},
  "description": {"en": "Hue-offset slider drops brand-recall accuracy with 4 brand swatches (exact vs offset) and Gaussian-fall-off accuracy curve.", "ko": "색조 오프셋 슬라이더로 브랜드 기억 정확도 하락 및 4개 브랜드 스와치(정확 vs 오프셋)와 가우시안 감소 곡선을 표시합니다."},
  "tier": "reference", "bloom_level": "L2", "domain": 12, "category": "marketing-and-branding",
  "layout": "A", "prerequisites": [], "leads_to": [], "see_also": [],
  "textbook_refs": [{"source": "Singh 2006", "section": "Color marketing"}],
  "standards": [], "interaction_count": 1, "learning_paths": ["designers-path"],
  "seo_keywords": ["brand recall", "Pantone trademark", "Tiffany Blue"],
  "estimated_hours": 8, "status": "shipped"
}
